cerise_client/__init__.py
cerise_client/errors.py
cerise_client/job.py
cerise_client/output_file.py
cerise_client/service.py
cerise_client-0.3.1.dist-info/DESCRIPTION.rst
cerise_client-0.3.1.dist-info/METADATA
cerise_client-0.3.1.dist-info/RECORD
cerise_client-0.3.1.dist-info/WHEEL
cerise_client-0.3.1.dist-info/metadata.json
cerise_client-0.3.1.dist-info/top_level.txt
