Metadata-Version: 2.0
Name: cerise-client
Version: 0.3.1
Summary: Client library for the Cerise CWL job running service
Home-page: https://github.com/MD-Studio/cerise-client
Author: Lourens Veen
Author-email: l.veen@esciencecenter.nl
License: Apache License 2.0
Download-URL: https://github.com/MD-Studio/cerise-client/archive/develop.tar.gz
Keywords: CWL,workflow,HPC
Platform: UNKNOWN
Classifier: Development Status :: 4 - Beta
Classifier: License :: OSI Approved :: Apache Software License
Classifier: Operating System :: POSIX :: Linux
Classifier: Programming Language :: Python :: 2.7
Classifier: Programming Language :: Python :: 3.5
Classifier: Programming Language :: Python :: 3.6
Classifier: Topic :: System :: Distributed Computing
Requires-Python: >=2.7, !=3.0.*, !=3.1.*, !=3.2.*, !=3.3.*, !=3.4.*, <4
Requires-Dist: defusedxml
Requires-Dist: future
Requires-Dist: requests
